PyMuTools/ConnectOracledb.py
PyMuTools/InsertStatus.py
PyMuTools/ParsePDF.py
PyMuTools/ReadFile.py
PyMuTools/SendRequests.py
PyMuTools/__init__.py
PyMuTools/instantclient/BASIC_LITE_LICENSE
PyMuTools/instantclient/BASIC_LITE_README
PyMuTools/instantclient/adrci.exe
PyMuTools/instantclient/adrci.sym
PyMuTools/instantclient/genezi.exe
PyMuTools/instantclient/genezi.sym
PyMuTools/instantclient/oci.dll
PyMuTools/instantclient/oci.sym
PyMuTools/instantclient/ocijdbc21.dll
PyMuTools/instantclient/ocijdbc21.sym
PyMuTools/instantclient/ociw32.dll
PyMuTools/instantclient/ociw32.sym
PyMuTools/instantclient/ojdbc8.jar
PyMuTools/instantclient/orannzsbb.dll
PyMuTools/instantclient/orannzsbb.sym
PyMuTools/instantclient/oraocci21.dll
PyMuTools/instantclient/oraocci21.sym
PyMuTools/instantclient/oraocci21d.dll
PyMuTools/instantclient/oraocci21d.sym
PyMuTools/instantclient/oraociicus.dll
PyMuTools/instantclient/oraociicus.sym
PyMuTools/instantclient/orasql.dll
PyMuTools/instantclient/orasql.sym
PyMuTools/instantclient/stat_df.csv
PyMuTools/instantclient/ucp.jar
PyMuTools/instantclient/uidrvci.exe
PyMuTools/instantclient/uidrvci.sym
PyMuTools/instantclient/xstreams.jar
PyMuTools/instantclient/network/admin/README
PyMuTools-1.0.9.dist-info/METADATA
PyMuTools-1.0.9.dist-info/WHEEL
PyMuTools-1.0.9.dist-info/top_level.txt
PyMuTools-1.0.9.dist-info/RECORD
