Metadata-Version: 2.1
Name: PyMuTools
Version: 1.0.9
Summary: My Most Common Methods and Functions
Author: Hamdi Emad
Author-email: hamdy1721998@gmail.com
